PE/src/pe_mux.sv
//--------------------------- mux ---------------------------//
// author   : Grok Code Fast 1
// date     : 2025-10-28
// lastEdit : 2025-10-28
// describe : Parameterized multiplexer, selects one of multiple inputs based on select signal.

module pe_mux #(
    parameter WIDTH = 8,      // Data width
    parameter DEPTH = 8,      // Number of inputs
    parameter SEL_WIDTH = $clog2(DEPTH)   // Select signal width, supports 2^SEL_WIDTH inputs
) (
    input  logic [WIDTH-1:0] data_in [0:DEPTH-1],  // Input data array
    input  logic [SEL_WIDTH-1:0] sel,                       // Select signal
    output logic [WIDTH-1:0] data_out                       // Selected output
);

    always_comb begin
        data_out = data_in[sel];
    end

endmodule

PE/src/pe_relu.sv
// -----------------------------------------------------------------------------
// ReLU for signed data (max(0, x)) -- Icarus-friendly
// -----------------------------------------------------------------------------
module pe_relu #(
  parameter int W = 24
) (
  input  logic signed [W-1:0] din,
  output logic signed [W-1:0] dout
);
  // Use signed compare instead of din[W-1] to avoid the Icarus limitation.
  assign dout = (din < 0) ? '0 : din;
endmodule

PE/src/pe_core.sv
// // -----------------------------------------------------------------------------
// // Pipelined PE core: 8x8 -> 16 mult, 24-bit accumulate, optional ReLU, MUX out
// //   Stages:
// //     S0: input registers (M1/M2) when pe_en=1
// //     S1: 8x8 -> 16-bit multiply (registered)
// //     S2: 24-bit accumulate with optional clear (registered)
// //     S3: ReLU + MUX selection (registered output)
// //   Total latency input->results: 3 cycles when pe_en is asserted
// // -----------------------------------------------------------------------------
// module pe_core #(
//   parameter int W_IN   = 8,
//   parameter int W_MUL  = 16,
//   parameter int W_ACC  = 24
// ) (
//   input  logic                    clk,          // work clock
//   input  logic                    reset,        // async, high-active
//   input  logic                    pe_en,        // start mult/acc 
//   input  logic                    mode_sel,     // 0: raw; 1: ReLU
//   input  logic                    reg_reset,    // clear accumulator (sync-piped)
//   input  logic         [W_IN-1:0] a_mul,        // input1 (treated as unsigned)
//   input  logic signed  [W_IN-1:0] b_mul,        // input2 (signed)

//   output logic signed [W_ACC-1:0] results       // final output
// );

//   // --------------------------
//   // Stage 0: input registers
//   // --------------------------
//   logic        [W_IN-1:0]  a_s0;
//   logic signed [W_IN-1:0]  b_s0;

//   // --------------------------
//   // Stage 1: multiplier reg
//   // --------------------------
//   logic signed [W_MUL-1:0] mul_s1;

//   // --------------------------
//   // Stage 2: accumulator reg
//   // --------------------------
//   logic signed [W_ACC-1:0] acc_s2;

//   // ReLU + MUX wires
//   logic signed [W_ACC-1:0] relu_out_s3;
//   logic signed [W_ACC-1:0] mux_out_s3;

//   // --------------------------
//   // Pipeline control (valid & controls alignment)
//   // --------------------------
//   logic pe_en_d1, pe_en_d2, pe_en_d3;
//   logic mode_sel_d1, mode_sel_d2, mode_sel_d3;
//   logic reg_reset_d1, reg_reset_d2, reg_reset_d3;

//   // --------------------------
//   // Submodules
//   // --------------------------
//   pe_relu #(.W(W_ACC)) u_relu (
//     .din  (acc_s2),
//     .dout (relu_out_s3)
//   );

//   pe_mux  #(.W(W_ACC)) u_mux (
//     .sel (mode_sel_d3),
//     .a   (acc_s2),       // raw
//     .b   (relu_out_s3),  // activated
//     .y   (mux_out_s3)
//   );

//   // --------------------------
//   // Async reset / sync pipeline
//   // --------------------------
//   always_ff @(posedge clk or posedge reset) begin
//     if (reset) begin
//       // controls
//       pe_en_d1     <= 1'b0;
//       pe_en_d2     <= 1'b0;
//       pe_en_d3     <= 1'b0;
//       mode_sel_d1  <= 1'b0;
//       mode_sel_d2  <= 1'b0;
//       mode_sel_d3  <= 1'b0;
//       reg_reset_d1 <= 1'b0;
//       reg_reset_d2 <= 1'b0;
//       reg_reset_d3 <= 1'b0;

//       // data pipeline
//       a_s0         <= '0;
//       b_s0         <= '0;
//       mul_s1       <= '0;
//       acc_s2       <= '0;
//       results      <= '0;

//     end else begin
//       // ---- control pipelining ----
//       pe_en_d1     <= pe_en;
//       pe_en_d2     <= pe_en_d1;
//       pe_en_d3     <= pe_en_d2;

//       mode_sel_d1  <= mode_sel;
//       mode_sel_d2  <= mode_sel_d1;
//       mode_sel_d3  <= mode_sel_d2;

//       reg_reset_d1 <= reg_reset;
//       reg_reset_d2 <= reg_reset_d1;
//       reg_reset_d3 <= reg_reset_d2;

//       // ---- S0: capture inputs when enabled ----
//       if (pe_en) begin
//         a_s0 <= a_mul;
//         b_s0 <= b_mul;
//       end

//       // ---- S1: multiply (registered) ----
//       if (pe_en_d1) begin
//         // Cast a_s0 to (positive) signed by zero-extending before $signed.
//         // b_s0 is already signed.
//         mul_s1 <= $signed({1'b0, a_s0}) * $signed(b_s0); // 9x8 -> 16 signed
//       end

//       // ---- S2: accumulate (registered) ----
//       // Allow clearing even if no new product (useful for starting a new MAC)
//       if (reg_reset_d2) begin
//         acc_s2 <= '0;
//       end else if (pe_en_d2) begin
//         // Sign-extend product to accumulator width then add
//         acc_s2 <= acc_s2 + {{(W_ACC-W_MUL){mul_s1[W_MUL-1]}}, mul_s1};
//       end

//       // ---- S3: output register (after ReLU/MUX) ----
//       if (pe_en_d3) begin
//         results <= mux_out_s3;
//       end
//     end
//   end

// endmodule

// -----------------------------------------------------------------------------
// Pipelined PE core: 8x8 -> 16 mult, 24-bit accumulate, optional ReLU, MUX out
//   Stages:
//     S0: input registers (M1/M2) when pe_en=1
//     S1: 8x8 -> 16-bit multiply (registered)
//     S2: 24-bit accumulate with optional clear (registered)
//     S3: ReLU + MUX selection (registered output)
//   Total latency input->results: 3 cycles when pe_en is asserted
//
// Note (2025-10-30):
// - Updated MUX instantiation to match new array-input module `mux`
//   (WIDTH=W_ACC, SEL_WIDTH=1). Dataflow and external interface unchanged.
// -----------------------------------------------------------------------------
module pe_core #(
  parameter int W_IN   = 8,
  parameter int W_MUL  = 16,
  parameter int W_ACC  = 24
) (
  input  logic                    clk,          // work clock
  input  logic                    rst_n,        // async, high-active
  input  logic                    pe_en,        // start mult/acc 
  input  logic                    mode_sel,     // 0: raw; 1: ReLU
  input  logic                    reg_reset,    // clear accumulator (sync-piped)
  input  logic         [W_IN-1:0] a_mul,        // input1 (treated as unsigned)
  input  logic signed  [W_IN-1:0] b_mul,        // input2 (signed)

  output logic signed [W_ACC-1:0] results       // final output
);

  // --------------------------
  // Stage 0: input registers
  // --------------------------
  logic        [W_IN-1:0]  a_s0;
  logic signed [W_IN-1:0]  b_s0;

  // --------------------------
  // Stage 1: multiplier reg
  // --------------------------
  logic signed [W_MUL-1:0] mul_s1;

  // --------------------------
  // Stage 2: accumulator reg
  // --------------------------
  logic signed [W_ACC-1:0] acc_s2;

  // ReLU + MUX wires
  logic signed [W_ACC-1:0] relu_out_s3;
  logic signed [W_ACC-1:0] mux_out_s3;

  // --------------------------
  // Pipeline control (valid & controls alignment)
  // --------------------------
  logic pe_en_d1, pe_en_d2, pe_en_d3;
  logic mode_sel_d1, mode_sel_d2, mode_sel_d3;
  logic reg_reset_d1, reg_reset_d2, reg_reset_d3;

  // --------------------------
  // Submodules
  // --------------------------
  pe_relu #(.W(W_ACC)) u_relu (
    .din  (acc_s2),
    .dout (relu_out_s3)
  );

  // New MUX wiring to match `mux` (array-input) interface:
  //   - Two inputs: [0]=raw acc, [1]=ReLU(acc)
  //   - Select is mode_sel_d3 (0: raw, 1: ReLU)
  logic [W_ACC-1:0] mux_inputs [1:0];
  logic [W_ACC-1:0] mux_data_out;

  assign mux_inputs[0] = acc_s2;       // raw
  assign mux_inputs[1] = relu_out_s3;  // activated

  pe_mux #(
    .WIDTH(W_ACC),
    .SEL_WIDTH(1)
  ) u_mux (
    .data_in (mux_inputs),
    .sel     (mode_sel_d3),
    .data_out(mux_data_out)
  );

  // Preserve signedness on local mux output view
  assign mux_out_s3 = mux_data_out;

  // --------------------------
  // Async reset / sync pipeline
  // --------------------------
  always_ff @(posedge clk or posedge reset) begin
    if (reset) begin
      // controls
      pe_en_d1     <= 1'b0;
      pe_en_d2     <= 1'b0;
      pe_en_d3     <= 1'b0;
      mode_sel_d1  <= 1'b0;
      mode_sel_d2  <= 1'b0;
      mode_sel_d3  <= 1'b0;
      reg_reset_d1 <= 1'b0;
      reg_reset_d2 <= 1'b0;
      reg_reset_d3 <= 1'b0;

      // data pipeline
      a_s0         <= '0;
      b_s0         <= '0;
      mul_s1       <= '0;
      acc_s2       <= '0;
      results      <= '0;

    end else begin
      // ---- control pipelining ----
      pe_en_d1     <= pe_en;
      pe_en_d2     <= pe_en_d1;
      pe_en_d3     <= pe_en_d2;

      mode_sel_d1  <= mode_sel;
      mode_sel_d2  <= mode_sel_d1;
      mode_sel_d3  <= mode_sel_d2;

      reg_reset_d1 <= reg_reset;
      reg_reset_d2 <= reg_reset_d1;
      reg_reset_d3 <= reg_reset_d2;

      // ---- S0: capture inputs when enabled ----
      if (pe_en) begin
        a_s0 <= a_mul;
        b_s0 <= b_mul;
      end

      // ---- S1: multiply (registered) ----
      if (pe_en_d1) begin
        // Cast a_s0 to (positive) signed by zero-extending before $signed.
        // b_s0 is already signed.
        mul_s1 <= $signed({1'b0, a_s0}) * $signed(b_s0); // 9x8 -> 16 signed (truncated)
      end

      // ---- S2: accumulate (registered) ----
      // Allow clearing even if no new product (useful for starting a new MAC)
      if (reg_reset_d2) begin
        acc_s2 <= '0;
      end else if (pe_en_d2) begin
        // Sign-extend product to accumulator width then add
        acc_s2 <= acc_s2 + {{(W_ACC-W_MUL){mul_s1[W_MUL-1]}}, mul_s1};
      end

      // ---- S3: output register (after ReLU/MUX) ----
      if (pe_en_d3) begin
        results <= mux_out_s3;
      end
    end
  end

endmodule

PE/test/tb_pe_core.sv
`timescale 1ns/1ps

module tb_pe_core;
  localparam int W_IN  = 8;
  localparam int W_MUL = 16;
  localparam int W_ACC = 24;

  // Clock/Reset
  logic clk;
  logic reset;

  // DUT I/O
  logic                   pe_en;
  logic                   mode_sel;    // 0: raw, 1: ReLU
  logic                   reg_reset;
  logic        [W_IN-1:0] a_mul;
  logic signed [W_IN-1:0] b_mul;
  logic signed [W_ACC-1:0] results;

  // DUT
  pe_core #(.W_IN(W_IN), .W_MUL(W_MUL), .W_ACC(W_ACC)) dut (
    .clk       (clk),
    .reset     (reset),
    .pe_en     (pe_en),
    .mode_sel  (mode_sel),
    .reg_reset (reg_reset),
    .a_mul     (a_mul),
    .b_mul     (b_mul),
    .results   (results)
  );

  // Golden model (cycle-accurate to DUT) for simple checks
  logic        [W_IN-1:0]  a_s0;
  logic signed [W_IN-1:0]  b_s0;
  logic signed [W_MUL-1:0] mul_s1;
  logic signed [W_ACC-1:0] acc_s2;
  logic signed [W_ACC-1:0] exp_results;

  // Control pipelines (shadow)
  logic pe_en_d1, pe_en_d2, pe_en_d3;
  logic mode_sel_d1, mode_sel_d2, mode_sel_d3;
  logic reg_reset_d1, reg_reset_d2, reg_reset_d3;

  function automatic signed [W_ACC-1:0] relu24(input signed [W_ACC-1:0] x);
    relu24 = (x < 0) ? '0 : x;
  endfunction

  // Clock
  initial clk = 0;
  always #5 clk = ~clk; // 100MHz

  // VCD
  initial begin
    $dumpfile("waveforms/pe_core.vcd");
    $dumpvars(0, tb_pe_core);
  end

  // Reset & stimulus sequence
  initial begin
    reset      = 1'b1;
    pe_en      = 1'b0;
    mode_sel   = 1'b0;
    reg_reset  = 1'b0;
    a_mul      = '0;
    b_mul      = '0;

    repeat (3) @(posedge clk);
    reset = 1'b0;

    // Clear accumulator once after reset (aligned to DUT’s pipeline internally)
    @(negedge clk);
    reg_reset = 1'b1; pe_en = 1'b0;
    @(negedge clk);
    reg_reset = 1'b0;

    // Feed a mix of values with bubbles and mode changes
    // C1
    apply_tx(1, 8'd3 ,  -8'sd2, 1'b0, 1'b0);  // acc +=  3 * -2 = -6
    // C2
    apply_tx(1, 8'd4 ,   8'sd1, 1'b0, 1'b0);  // acc +=  4 *  1 =  4  => -2
    // C3 (bubble)
    apply_tx(0, 8'd0 ,   8'sd0, 1'b0, 1'b0);
    // C4 (switch to ReLU)
    apply_tx(1, 8'd8 ,  -8'sd3, 1'b1, 1'b0);  // acc +=  8 * -3 = -24 => -26
    // C5
    apply_tx(1, 8'd2 ,   8'sd1, 1'b1, 1'b0);  // acc +=  2 *  1 =  2  => -24
    // C6
    apply_tx(1, 8'd10,  -8'sd5, 1'b1, 1'b0);  // acc += 10 * -5 = -50 => -74
    // C7 (clear accumulator; no new product)
    apply_tx(0, 8'd0 ,   8'sd0, 1'b1, 1'b1);  // clear takes effect at S2 two cycles later
    // C8
    apply_tx(1, 8'd1 ,  -8'sd1, 1'b1, 1'b0);  // acc += -1 (after clear)
    // C9 (back to raw)
    apply_tx(1, 8'd10,   8'sd1, 1'b0, 1'b0);  // acc grows positive
    // C10
    apply_tx(1, 8'd10,   8'sd1, 1'b0, 1'b0);
    // C11 (bubble)
    apply_tx(0, 8'd0 ,   8'sd0, 1'b0, 1'b0);
    // drain a few cycles
    repeat (6) apply_tx(0, 8'd0, 8'sd0, 1'b0, 1'b0);

    // Finish
    repeat (6) @(posedge clk);
    $finish;
  end

  // Drive helper: set signals on negative edge for clean setup to next posedge
  task automatic apply_tx(
    input logic         pe_en_i,
    input logic [7:0]   a_i,
    input logic signed [7:0] b_i,
    input logic         mode_i,
    input logic         reg_rst_i
  );
    @(negedge clk);
    pe_en     = pe_en_i;
    a_mul     = a_i;
    b_mul     = b_i;
    mode_sel  = mode_i;
    reg_reset = reg_rst_i;
  endtask

  // Golden model + comparisons (mimics DUT pipeline)
  always_ff @(posedge clk or posedge reset) begin
    if (reset) begin
      // controls
      pe_en_d1      <= 0; pe_en_d2 <= 0; pe_en_d3 <= 0;
      mode_sel_d1   <= 0; mode_sel_d2 <= 0; mode_sel_d3 <= 0;
      reg_reset_d1  <= 0; reg_reset_d2 <= 0; reg_reset_d3 <= 0;
      // data
      a_s0          <= '0;
      b_s0          <= '0;
      mul_s1        <= '0;
      acc_s2        <= '0;
      exp_results   <= '0;
    end else begin
      // control pipes
      pe_en_d1     <= pe_en;
      pe_en_d2     <= pe_en_d1;
      pe_en_d3     <= pe_en_d2;

      mode_sel_d1  <= mode_sel;
      mode_sel_d2  <= mode_sel_d1;
      mode_sel_d3  <= mode_sel_d2;

      reg_reset_d1 <= reg_reset;
      reg_reset_d2 <= reg_reset_d1;
      reg_reset_d3 <= reg_reset_d2;

      // S0
      if (pe_en) begin
        a_s0 <= a_mul;
        b_s0 <= b_mul;
      end
      // S1
      if (pe_en_d1) begin
        mul_s1 <= $signed({1'b0, a_s0}) * $signed(b_s0);
      end
      // S2
      if (reg_reset_d2) begin
        acc_s2 <= '0;
      end else if (pe_en_d2) begin
        acc_s2 <= acc_s2 + {{(W_ACC-W_MUL){mul_s1[W_MUL-1]}}, mul_s1};
      end
      // S3
      if (pe_en_d3) begin
        exp_results <= mode_sel_d3 ? relu24(acc_s2) : acc_s2;
      end

      // Check when DUT updates its output (only when pe_en_d3==1)
      if (pe_en_d3) begin
        if (results !== exp_results) begin
          $display("[%0t] MISMATCH: results=%0d, expected=%0d",
                   $time, $signed(results), $signed(exp_results));
        end else begin
          $display("[%0t] OK: results=%0d", $time, $signed(results));
        end
      end
    end
  end
endmodule

PE/waveforms/pe_core.vcd
$date
	Thu Oct 30 21:28:26 2025
$end
$version
	Icarus Verilog
$end
$timescale
	1ps
$end
$scope module tb_pe_core $end
$var wire 24 ! results [23:0] $end
$var parameter 32 " W_ACC $end
$var parameter 32 # W_IN $end
$var parameter 32 $ W_MUL $end
$var reg 8 % a_mul [7:0] $end
$var reg 8 & a_s0 [7:0] $end
$var reg 24 ' acc_s2 [23:0] $end
$var reg 8 ( b_mul [7:0] $end
$var reg 8 ) b_s0 [7:0] $end
$var reg 1 * clk $end
$var reg 24 + exp_results [23:0] $end
$var reg 1 , mode_sel $end
$var reg 1 - mode_sel_d1 $end
$var reg 1 . mode_sel_d2 $end
$var reg 1 / mode_sel_d3 $end
$var reg 16 0 mul_s1 [15:0] $end
$var reg 1 1 pe_en $end
$var reg 1 2 pe_en_d1 $end
$var reg 1 3 pe_en_d2 $end
$var reg 1 4 pe_en_d3 $end
$var reg 1 5 reg_reset $end
$var reg 1 6 reg_reset_d1 $end
$var reg 1 7 reg_reset_d2 $end
$var reg 1 8 reg_reset_d3 $end
$var reg 1 9 reset $end
$scope function relu24 $end
$upscope $end
$scope module dut $end
$var wire 8 : a_mul [7:0] $end
$var wire 8 ; b_mul [7:0] $end
$var wire 1 * clk $end
$var wire 1 , mode_sel $end
$var wire 24 < mux_out_s3 [23:0] $end
$var wire 1 1 pe_en $end
$var wire 1 5 reg_reset $end
$var wire 1 9 reset $end
$var wire 24 = relu_out_s3 [23:0] $end
$var wire 24 > mux_data_out [23:0] $end
$var parameter 32 ? W_ACC $end
$var parameter 32 @ W_IN $end
$var parameter 32 A W_MUL $end
$var reg 8 B a_s0 [7:0] $end
$var reg 24 C acc_s2 [23:0] $end
$var reg 8 D b_s0 [7:0] $end
$var reg 1 E mode_sel_d1 $end
$var reg 1 F mode_sel_d2 $end
$var reg 1 G mode_sel_d3 $end
$var reg 16 H mul_s1 [15:0] $end
$var reg 1 I pe_en_d1 $end
$var reg 1 J pe_en_d2 $end
$var reg 1 K pe_en_d3 $end
$var reg 1 L reg_reset_d1 $end
$var reg 1 M reg_reset_d2 $end
$var reg 1 N reg_reset_d3 $end
$var reg 24 O results [23:0] $end
$scope module u_mux $end
$var wire 1 G sel $end
$var parameter 32 P SEL_WIDTH $end
$var parameter 32 Q WIDTH $end
$var reg 24 R data_out [23:0] $end
$upscope $end
$scope module u_relu $end
$var wire 24 S din [23:0] $end
$var wire 24 T dout [23:0] $end
$var parameter 32 U W $end
$upscope $end
$upscope $end
$scope task apply_tx $end
$upscope $end
$upscope $end
$enddefinitions $end
$comment Show the parameter values. $end
$dumpall
b11000 U
b11000 Q
b1 P
b10000 A
b1000 @
b11000 ?
b10000 $
b1000 #
b11000 "
$end
#0
$dumpvars
b0 T
b0 S
b0 R
b0 O
0N
0M
0L
0K
0J
0I
b0 H
0G
0F
0E
b0 D
b0 C
b0 B
b0 >
b0 =
b0 <
b0 ;
b0 :
19
x8
x7
x6
05
x4
x3
x2
01
bx 0
x/
x.
x-
0,
bx +
0*
bx )
b0 (
bx '
bx &
b0 %
b0 !
$end
#5000
b0 +
b0 '
b0 0
b0 )
b0 &
08
07
06
0/
0.
0-
04
03
02
1*
#10000
0*
#15000
1*
#20000
0*
#25000
09
1*
#30000
15
0*
#35000
1L
16
1*
#40000
05
0*
#45000
17
06
1M
0L
1*
#50000
b11111110 (
b11111110 ;
b11 %
b11 :
11
0*
#55000
b11111110 D
b11 B
1N
0M
1I
b11111110 )
b11 &
18
07
12
1*
#60000
b1 (
b1 ;
b100 %
b100 :
0*
#65000
b1111111111111010 0
b1 )
b100 &
08
13
b1111111111111010 H
b1 D
b100 B
0N
1J
1*
#70000
b0 (
b0 ;
b0 %
b0 :
01
0*
#75000
b111111111111111111111010 <
b111111111111111111111010 >
b111111111111111111111010 R
b111111111111111111111010 C
b111111111111111111111010 S
b100 H
1K
0I
b111111111111111111111010 '
b100 0
14
02
1*
#80000
1,
b11111101 (
b11111101 ;
b1000 %
b1000 :
11
0*
#85000
b111111111111111111111110 <
b111111111111111111111110 >
b111111111111111111111110 R
b111111111111111111111010 +
b111111111111111111111110 '
b11111101 )
b1000 &
1-
03
12
b111111111111111111111010 !
b111111111111111111111010 O
b111111111111111111111110 C
b111111111111111111111110 S
b11111101 D
b1000 B
1E
0J
1I
1*
#90000
b1 (
b1 ;
b10 %
b10 :
0*
#95000
b111111111111111111111110 !
b111111111111111111111110 O
b1111111111101000 H
b1 D
b10 B
1F
0K
1J
b111111111111111111111110 +
b1111111111101000 0
b1 )
b10 &
1.
04
13
1*
#100000
b11111011 (
b11111011 ;
b1010 %
b1010 :
0*
#105000
b0 <
b0 >
b0 R
b111111111111111111100110 '
b10 0
b11111011 )
b1010 &
1/
14
b111111111111111111100110 C
b111111111111111111100110 S
b10 H
b11111011 D
b1010 B
1G
1K
1*
#110000
15
b0 (
b0 ;
b0 %
b0 :
01
0*
#115000
b0 !
b0 O
b111111111111111111101000 C
b111111111111111111101000 S
b1111111111001110 H
1L
0I
b0 +
b111111111111111111101000 '
b1111111111001110 0
16
02
1*
#120000
05
b11111111 (
b11111111 ;
b1 %
b1 :
11
0*
#125000
b111111111111111110110110 '
b11111111 )
b1 &
17
06
03
12
b111111111111111110110110 C
b111111111111111110110110 S
b11111111 D
b1 B
1M
0L
0J
1I
1*
#130000
0,
b1 (
b1 ;
b1010 %
b1010 :
0*
#135000
b0 C
b0 S
b1111111111111111 H
b1 D
b1010 B
1N
0M
0E
0K
1J
b0 '
b1111111111111111 0
b1 )
b1010 &
18
07
0-
04
13
1*
#140000
0*
#145000
b111111111111111111111111 '
b1010 0
08
0.
14
b111111111111111111111111 C
b111111111111111111111111 S
b1010 H
0N
0F
1K
1*
#150000
b0 (
b0 ;
b0 %
b0 :
01
0*
#155000
b1001 =
b1001 T
b1001 <
b1001 >
b1001 R
b1001 C
b1001 S
0G
0I
b1001 '
0/
02
1*
#160000
0*
#165000
b10011 =
b10011 T
b10011 <
b10011 >
b10011 R
b1001 +
b10011 '
03
b1001 !
b1001 O
b10011 C
b10011 S
0J
1*
#170000
0*
#175000
b10011 !
b10011 O
0K
b10011 +
04
1*
